[
  {
    "id": 928265320,
    "name": "zs-cc-vpc-01234567890abcdef-us-east-1-zscc-test-cc-asg-1-91lr0e70",
    "deployType": "CLOUD",
    "fallBackToTls": false,
    "status": [
      "CLOUD",
      "AUTO_SCALE"
    ],
    "autoScale": true,
    "platform": "AWS",
    "awsRegion": "US_EAST_1",
    "location": {
      "id": 898381331,
      "name": "test-us_use1-us-east-1-vpc-01234567890abcdef"
    },
    "ecVMs": [
      {
        "id": 894279614,
        "name": "zs-cc-vpc-01234567890abcdef-us-east-1-zscc-test-cc-asg-1-91lr0e70-VM-hrKqb",
        "status": [
          "REGISTERED",
          "PKG_REPO_REGISTERED",
          "DELETING",
          "AUTO_SCALE"
        ],
        "autoScale": true,
        "operationalStatus": "INACTIVE",
        "formFactor": "SMALL",
        "ziaGateway": "",
        "zpaBroker": "",
        "upgradeStatus": 1,
        "upgradeStartTime": 14400,
        "upgradeEndTime": 21600,
        "upgradeDayOfWeek": 1,
        "haStatus": "DISABLED",
        "useWanDns": false,
        "usedForZtp": false,
        "dnsCache": false,
        "failOpen": false,
        "ziaGateways": [],
        "zpaBrokers": []
      },
      {
        "id": 941969343,
        "name": "zs-cc-vpc-01234567890abcdef-us-east-1-zscc-test-cc-asg-1-91lr0e70-VM-qmXlu",
        "status": [
          "REGISTERED",
          "PKG_REPO_REGISTERED",
          "AUTO_SCALE"
        ],
        "autoScale": true,
        "operationalStatus": "INACTIVE",
        "formFactor": "SMALL",
        "ziaGateway": "",
        "zpaBroker": "",
        "buildVersion": "0.171.17+a59ce5f6_6.2.25336+566e22ec",
        "upgradeStatus": 0,
        "upgradeStartTime": 0,
        "upgradeEndTime": 7200,
        "upgradeDayOfWeek": 1,
        "haStatus": "DISABLED",
        "useWanDns": false,
        "usedForZtp": false,
        "dnsCache": false,
        "failOpen": false,
        "ziaGateways": [],
        "zpaBrokers": []
      },
      {
        "id": 611893721,
        "name": "zs-cc-vpc-01234567890abcdef-us-east-1-zscc-test-cc-asg-1-91lr0e70-VM-xIAeT",
        "status": [
          "REGISTERED",
          "PKG_REPO_REGISTERED",
          "AUTO_SCALE"
        ],
        "autoScale": true,
        "operationalStatus": "INACTIVE",
        "formFactor": "SMALL",
        "ziaGateway": "",
        "zpaBroker": "",
        "upgradeStatus": 1,
        "upgradeStartTime": 0,
        "upgradeEndTime": 7200,
        "upgradeDayOfWeek": 1,
        "haStatus": "DISABLED",
        "useWanDns": false,
        "usedForZtp": false,
        "dnsCache": false,
        "failOpen": false,
        "ziaGateways": [],
        "zpaBrokers": []
      },
      {
        "id": 272273026,
        "name": "zs-cc-vpc-01234567890abcdef-us-east-1-zscc-test-cc-asg-1-91lr0e70-VM-9dsaW",
        "status": [
          "REGISTERED",
          "PKG_REPO_REGISTERED",
          "AUTO_SCALE"
        ],
        "autoScale": true,
        "operationalStatus": "INACTIVE",
        "formFactor": "SMALL",
        "ziaGateway": "",
        "zpaBroker": "",
        "upgradeStatus": 1,
        "upgradeStartTime": 0,
        "upgradeEndTime": 7200,
        "upgradeDayOfWeek": 1,
        "haStatus": "DISABLED",
        "useWanDns": false,
        "usedForZtp": false,
        "dnsCache": false,
        "failOpen": false,
        "ziaGateways": [],
        "zpaBrokers": []
      },
      {
        "id": 673317173,
        "name": "zs-cc-vpc-01234567890abcdef-us-east-1-zscc-test-cc-asg-1-91lr0e70-VM-N9PAi",
        "status": [
          "REGISTERED",
          "PKG_REPO_REGISTERED",
          "AUTO_SCALE"
        ],
        "autoScale": true,
        "operationalStatus": "INACTIVE",
        "formFactor": "SMALL",
        "ziaGateway": "",
        "zpaBroker": "",
        "upgradeStatus": 1,
        "upgradeStartTime": 0,
        "upgradeEndTime": 7200,
        "upgradeDayOfWeek": 1,
        "haStatus": "DISABLED",
        "useWanDns": false,
        "usedForZtp": false,
        "dnsCache": false,
        "failOpen": false,
        "ziaGateways": [],
        "zpaBrokers": []
      },
      {
        "id": 696027130,
        "name": "zs-cc-vpc-01234567890abcdef-us-east-1-zscc-test-cc-asg-1-91lr0e70-VM-qDq9f",
        "status": [
          "REGISTERED",
          "PKG_REPO_REGISTERED",
          "AUTO_SCALE"
        ],
        "autoScale": true,
        "operationalStatus": "INACTIVE",
        "formFactor": "SMALL",
        "ziaGateway": "",
        "zpaBroker": "",
        "buildVersion": "0.209.6+5d1760079_6.2.29797+35e543fd",
        "upgradeStatus": 0,
        "upgradeStartTime": 0,
        "upgradeEndTime": 7200,
        "upgradeDayOfWeek": 1,
        "haStatus": "DISABLED",
        "useWanDns": false,
        "usedForZtp": false,
        "dnsCache": false,
        "failOpen": false,
        "ziaGateways": [],
        "zpaBrokers": []
      },
      {
        "id": 640491833,
        "name": "zs-cc-vpc-01234567890abcdef-us-east-1-zscc-test-cc-asg-1-91lr0e70-VM-kTCgl",
        "status": [
          "REGISTERED",
          "PKG_REPO_REGISTERED",
          "AUTO_SCALE"
        ],
        "autoScale": true,
        "operationalStatus": "INACTIVE",
        "formFactor": "SMALL",
        "ziaGateway": "",
        "zpaBroker": "",
        "upgradeStatus": 1,
        "upgradeStartTime": 0,
        "upgradeEndTime": 7200,
        "upgradeDayOfWeek": 1,
        "haStatus": "DISABLED",
        "useWanDns": false,
        "usedForZtp": false,
        "dnsCache": false,
        "failOpen": false,
        "ziaGateways": [],
        "zpaBrokers": []
      },
      {
        "id": 982374955,
        "name": "zs-cc-vpc-01234567890abcdef-us-east-1-zscc-test-cc-asg-1-91lr0e70-VM-5fqdV",
        "status": [
          "REGISTERED",
          "PKG_REPO_REGISTERED",
          "AUTO_SCALE"
        ],
        "autoScale": true,
        "operationalStatus": "INACTIVE",
        "formFactor": "SMALL",
        "ziaGateway": "",
        "zpaBroker": "",
        "upgradeStatus": 1,
        "upgradeStartTime": 0,
        "upgradeEndTime": 7200,
        "upgradeDayOfWeek": 1,
        "haStatus": "DISABLED",
        "useWanDns": false,
        "usedForZtp": false,
        "dnsCache": false,
        "failOpen": false,
        "ziaGateways": [],
        "zpaBrokers": []
      },
      {
        "id": 174902207,
        "name": "zs-cc-vpc-01234567890abcdef-us-east-1-zscc-test-cc-asg-1-91lr0e70-VM-tfXRQ",
        "status": [
          "REGISTERED",
          "PKG_REPO_REGISTERED",
          "AUTO_SCALE"
        ],
        "autoScale": true,
        "operationalStatus": "INACTIVE",
        "formFactor": "SMALL",
        "ziaGateway": "",
        "zpaBroker": "",
        "buildVersion": "0.209.6+5d1760079_6.2.29797+35e543fd",
        "upgradeStatus": 0,
        "upgradeStartTime": 0,
        "upgradeEndTime": 7200,
        "upgradeDayOfWeek": 1,
        "haStatus": "DISABLED",
        "useWanDns": false,
        "usedForZtp": false,
        "dnsCache": false,
        "failOpen": false,
        "ziaGateways": [],
        "zpaBrokers": []
      },
      {
        "id": 100962953,
        "name": "zs-cc-vpc-01234567890abcdef-us-east-1-zscc-test-cc-asg-1-91lr0e70-VM-j3Dl4",
        "status": [
          "REGISTERED",
          "PKG_REPO_REGISTERED",
          "AUTO_SCALE"
        ],
        "autoScale": true,
        "operationalStatus": "INACTIVE",
        "formFactor": "SMALL",
        "ziaGateway": "",
        "zpaBroker": "",
        "upgradeStatus": 1,
        "upgradeStartTime": 0,
        "upgradeEndTime": 7200,
        "upgradeDayOfWeek": 1,
        "haStatus": "DISABLED",
        "useWanDns": false,
        "usedForZtp": false,
        "dnsCache": false,
        "failOpen": false,
        "ziaGateways": [],
        "zpaBrokers": []
      },
      {
        "id": 809289808,
        "name": "zs-cc-vpc-01234567890abcdef-us-east-1-zscc-test-cc-asg-1-91lr0e70-VM-AayK8",
        "status": [
          "REGISTERED",
          "PKG_REPO_REGISTERED",
          "AUTO_SCALE"
        ],
        "autoScale": true,
        "operationalStatus": "INACTIVE",
        "formFactor": "SMALL",
        "ziaGateway": "",
        "zpaBroker": "",
        "buildVersion": "0.209.6+5d1760079_6.2.29797+35e543fd",
        "upgradeStatus": 0,
        "upgradeStartTime": 0,
        "upgradeEndTime": 7200,
        "upgradeDayOfWeek": 1,
        "haStatus": "DISABLED",
        "useWanDns": false,
        "usedForZtp": false,
        "dnsCache": false,
        "failOpen": false,
        "ziaGateways": [],
        "zpaBrokers": []
      },
      {
        "id": 246139622,
        "name": "zs-cc-vpc-01234567890abcdef-us-east-1-zscc-test-cc-asg-1-91lr0e70-VM-HUCOH",
        "status": [
          "REGISTERED",
          "PKG_REPO_REGISTERED",
          "AUTO_SCALE"
        ],
        "autoScale": true,
        "operationalStatus": "INACTIVE",
        "formFactor": "SMALL",
        "ziaGateway": "",
        "zpaBroker": "",
        "upgradeStatus": 1,
        "upgradeStartTime": 0,
        "upgradeEndTime": 7200,
        "upgradeDayOfWeek": 1,
        "haStatus": "DISABLED",
        "useWanDns": false,
        "usedForZtp": false,
        "dnsCache": false,
        "failOpen": false,
        "ziaGateways": [],
        "zpaBrokers": []
      },
      {
        "id": 128344214,
        "name": "zs-cc-vpc-01234567890abcdef-us-east-1-zscc-test-cc-asg-1-91lr0e70-VM-StTp0",
        "status": [
          "REGISTERED",
          "PKG_REPO_REGISTERED",
          "AUTO_SCALE"
        ],
        "autoScale": true,
        "operationalStatus": "ACTIVE",
        "formFactor": "SMALL",
        "ziaGateway": "",
        "zpaBroker": "",
        "buildVersion": "1.145.62_6.2.33187+17750d79",
        "upgradeStatus": 1,
        "upgradeStartTime": 0,
        "upgradeEndTime": 7200,
        "upgradeDayOfWeek": 1,
        "haStatus": "DISABLED",
        "useWanDns": false,
        "usedForZtp": false,
        "dnsCache": false,
        "failOpen": false,
        "ziaGateways": [],
        "zpaBrokers": []
      },
      {
        "id": 598420160,
        "name": "zs-cc-vpc-01234567890abcdef-us-east-1-zscc-test-cc-asg-1-91lr0e70-VM-PZmuW",
        "status": [
          "REGISTERED",
          "PKG_REPO_REGISTERED",
          "AUTO_SCALE"
        ],
        "autoScale": true,
        "operationalStatus": "ACTIVE",
        "formFactor": "SMALL",
        "ziaGateway": "",
        "zpaBroker": "",
        "buildVersion": "1.145.62_6.2.33187+17750d79",
        "upgradeStatus": 1,
        "upgradeStartTime": 0,
        "upgradeEndTime": 7200,
        "upgradeDayOfWeek": 1,
        "haStatus": "DISABLED",
        "useWanDns": false,
        "usedForZtp": false,
        "dnsCache": false,
        "failOpen": false,
        "ziaGateways": [],
        "zpaBrokers": []
      },
      {
        "id": 447361387,
        "name": "zs-cc-vpc-01234567890abcdef-us-east-1-zscc-test-cc-asg-1-91lr0e70-VM-VveeF",
        "status": [
          "REGISTERED",
          "PKG_REPO_REGISTERED",
          "AUTO_SCALE"
        ],
        "autoScale": true,
        "operationalStatus": "INACTIVE",
        "formFactor": "SMALL",
        "ziaGateway": "",
        "zpaBroker": "",
        "upgradeStatus": 1,
        "upgradeStartTime": 0,
        "upgradeEndTime": 7200,
        "upgradeDayOfWeek": 1,
        "haStatus": "DISABLED",
        "useWanDns": false,
        "usedForZtp": false,
        "dnsCache": false,
        "failOpen": false,
        "ziaGateways": [],
        "zpaBrokers": []
      }
    ]
  },
  {
    "id": 130827167,
    "name": "zs-cc-vpc-0fedcba9876543210-us-west-2-zscc-prod-cc-asg-1-3ofteftm",
    "deployType": "CLOUD",
    "fallBackToTls": false,
    "status": [
      "CLOUD",
      "AUTO_SCALE"
    ],
    "autoScale": true,
    "platform": "AWS",
    "awsRegion": "US_WEST_2",
    "location": {
      "id": 383089403,
      "name": "production-us_usw2-us-west-2-vpc-0fedcba9876543210"
    },
    "ecVMs": [
      {
        "id": 771298278,
        "name": "zs-cc-vpc-0fedcba9876543210-us-west-2-zscc-prod-cc-asg-1-3ofteftm-VM-KqsfE",
        "status": [
          "AUTO_SCALE"
        ],
        "autoScale": true,
        "operationalStatus": "INACTIVE",
        "formFactor": "SMALL",
        "ziaGateway": "",
        "zpaBroker": "",
        "upgradeStatus": 1,
        "upgradeStartTime": 0,
        "upgradeEndTime": 7200,
        "upgradeDayOfWeek": 1,
        "haStatus": "DISABLED",
        "useWanDns": false,
        "usedForZtp": false,
        "dnsCache": false,
        "failOpen": false,
        "ziaGateways": [],
        "zpaBrokers": []
      },
      {
        "id": 626708192,
        "name": "zs-cc-vpc-0fedcba9876543210-us-west-2-zscc-prod-cc-asg-1-3ofteftm-VM-1fQrU",
        "status": [
          "AUTO_SCALE"
        ],
        "autoScale": true,
        "operationalStatus": "INACTIVE",
        "formFactor": "SMALL",
        "ziaGateway": "",
        "zpaBroker": "",
        "upgradeStatus": 1,
        "upgradeStartTime": 0,
        "upgradeEndTime": 7200,
        "upgradeDayOfWeek": 1,
        "haStatus": "DISABLED",
        "useWanDns": false,
        "usedForZtp": false,
        "dnsCache": false,
        "failOpen": false,
        "ziaGateways": [],
        "zpaBrokers": []
      },
      {
        "id": 713575434,
        "name": "zs-cc-vpc-0fedcba9876543210-us-west-2-zscc-prod-cc-asg-1-3ofteftm-VM-YRQI8",
        "status": [
          "AUTO_SCALE"
        ],
        "autoScale": true,
        "operationalStatus": "INACTIVE",
        "formFactor": "SMALL",
        "ziaGateway": "",
        "zpaBroker": "",
        "upgradeStatus": 1,
        "upgradeStartTime": 0,
        "upgradeEndTime": 7200,
        "upgradeDayOfWeek": 1,
        "haStatus": "DISABLED",
        "useWanDns": false,
        "usedForZtp": false,
        "dnsCache": false,
        "failOpen": false,
        "ziaGateways": [],
        "zpaBrokers": []
      },
      {
        "id": 607605913,
        "name": "zs-cc-vpc-0fedcba9876543210-us-west-2-zscc-prod-cc-asg-1-3ofteftm-VM-GJdRZ",
        "status": [
          "AUTO_SCALE"
        ],
        "autoScale": true,
        "operationalStatus": "INACTIVE",
        "formFactor": "SMALL",
        "ziaGateway": "",
        "zpaBroker": "",
        "upgradeStatus": 1,
        "upgradeStartTime": 0,
        "upgradeEndTime": 7200,
        "upgradeDayOfWeek": 1,
        "haStatus": "DISABLED",
        "useWanDns": false,
        "usedForZtp": false,
        "dnsCache": false,
        "failOpen": false,
        "ziaGateways": [],
        "zpaBrokers": []
      },
      {
        "id": 569847415,
        "name": "zs-cc-vpc-0fedcba9876543210-us-west-2-zscc-prod-cc-asg-1-3ofteftm-VM-SA11k",
        "status": [
          "AUTO_SCALE"
        ],
        "autoScale": true,
        "operationalStatus": "INACTIVE",
        "formFactor": "SMALL",
        "ziaGateway": "",
        "zpaBroker": "",
        "upgradeStatus": 1,
        "upgradeStartTime": 0,
        "upgradeEndTime": 7200,
        "upgradeDayOfWeek": 1,
        "haStatus": "DISABLED",
        "useWanDns": false,
        "usedForZtp": false,
        "dnsCache": false,
        "failOpen": false,
        "ziaGateways": [],
        "zpaBrokers": []
      },
      {
        "id": 614374988,
        "name": "zs-cc-vpc-0fedcba9876543210-us-west-2-zscc-prod-cc-asg-1-3ofteftm-VM-uqPUd",
        "status": [
          "REGISTERED",
          "PKG_REPO_REGISTERED",
          "AUTO_SCALE"
        ],
        "autoScale": true,
        "operationalStatus": "INACTIVE",
        "formFactor": "SMALL",
        "ziaGateway": "",
        "zpaBroker": "",
        "upgradeStatus": 1,
        "upgradeStartTime": 0,
        "upgradeEndTime": 7200,
        "upgradeDayOfWeek": 1,
        "haStatus": "DISABLED",
        "useWanDns": false,
        "usedForZtp": false,
        "dnsCache": false,
        "failOpen": false,
        "ziaGateways": [],
        "zpaBrokers": []
      },
      {
        "id": 509803072,
        "name": "zs-cc-vpc-0fedcba9876543210-us-west-2-zscc-prod-cc-asg-1-3ofteftm-VM-8hlg5",
        "status": [
          "REGISTERED",
          "PKG_REPO_REGISTERED",
          "AUTO_SCALE"
        ],
        "autoScale": true,
        "operationalStatus": "INACTIVE",
        "formFactor": "SMALL",
        "ziaGateway": "",
        "zpaBroker": "",
        "upgradeStatus": 1,
        "upgradeStartTime": 0,
        "upgradeEndTime": 7200,
        "upgradeDayOfWeek": 1,
        "haStatus": "DISABLED",
        "useWanDns": false,
        "usedForZtp": false,
        "dnsCache": false,
        "failOpen": false,
        "ziaGateways": [],
        "zpaBrokers": []
      },
      {
        "id": 770108618,
        "name": "zs-cc-vpc-0fedcba9876543210-us-west-2-zscc-prod-cc-asg-1-3ofteftm-VM-rIZg6",
        "status": [
          "REGISTERED",
          "PKG_REPO_REGISTERED",
          "AUTO_SCALE"
        ],
        "autoScale": true,
        "operationalStatus": "INACTIVE",
        "formFactor": "SMALL",
        "ziaGateway": "",
        "zpaBroker": "",
        "buildVersion": "0.209.6+5d1760079_6.2.29797+35e543fd",
        "upgradeStatus": 0,
        "upgradeStartTime": 0,
        "upgradeEndTime": 7200,
        "upgradeDayOfWeek": 1,
        "haStatus": "DISABLED",
        "useWanDns": false,
        "usedForZtp": false,
        "dnsCache": false,
        "failOpen": false,
        "ziaGateways": [],
        "zpaBrokers": []
      },
      {
        "id": 858763744,
        "name": "zs-cc-vpc-0fedcba9876543210-us-west-2-zscc-prod-cc-asg-1-3ofteftm-VM-9THmZ",
        "status": [
          "REGISTERED",
          "PKG_REPO_REGISTERED",
          "AUTO_SCALE"
        ],
        "autoScale": true,
        "operationalStatus": "INACTIVE",
        "formFactor": "SMALL",
        "ziaGateway": "",
        "zpaBroker": "",
        "buildVersion": "0.209.6+5d1760079_6.2.29797+35e543fd",
        "upgradeStatus": 0,
        "upgradeStartTime": 0,
        "upgradeEndTime": 7200,
        "upgradeDayOfWeek": 1,
        "haStatus": "DISABLED",
        "useWanDns": false,
        "usedForZtp": false,
        "dnsCache": false,
        "failOpen": false,
        "ziaGateways": [],
        "zpaBrokers": []
      },
      {
        "id": 447123038,
        "name": "zs-cc-vpc-0fedcba9876543210-us-west-2-zscc-prod-cc-asg-1-3ofteftm-VM-jmf6z",
        "status": [
          "REGISTERED",
          "PKG_REPO_REGISTERED",
          "AUTO_SCALE"
        ],
        "autoScale": true,
        "operationalStatus": "INACTIVE",
        "formFactor": "SMALL",
        "ziaGateway": "",
        "zpaBroker": "",
        "buildVersion": "0.209.6+5d1760079_6.2.29797+35e543fd",
        "upgradeStatus": 0,
        "upgradeStartTime": 0,
        "upgradeEndTime": 7200,
        "upgradeDayOfWeek": 1,
        "haStatus": "DISABLED",
        "useWanDns": false,
        "usedForZtp": false,
        "dnsCache": false,
        "failOpen": false,
        "ziaGateways": [],
        "zpaBrokers": []
      },
      {
        "id": 662822714,
        "name": "zs-cc-vpc-0fedcba9876543210-us-west-2-zscc-prod-cc-asg-1-3ofteftm-VM-BjE42",
        "status": [
          "REGISTERED",
          "PKG_REPO_REGISTERED",
          "AUTO_SCALE"
        ],
        "autoScale": true,
        "operationalStatus": "INACTIVE",
        "formFactor": "SMALL",
        "ziaGateway": "",
        "zpaBroker": "",
        "upgradeStatus": 1,
        "upgradeStartTime": 0,
        "upgradeEndTime": 7200,
        "upgradeDayOfWeek": 1,
        "haStatus": "DISABLED",
        "useWanDns": false,
        "usedForZtp": false,
        "dnsCache": false,
        "failOpen": false,
        "ziaGateways": [],
        "zpaBrokers": []
      },
      {
        "id": 150004736,
        "name": "zs-cc-vpc-0fedcba9876543210-us-west-2-zscc-prod-cc-asg-1-3ofteftm-VM-mCKtN",
        "status": [
          "REGISTERED",
          "PKG_REPO_REGISTERED",
          "AUTO_SCALE"
        ],
        "autoScale": true,
        "operationalStatus": "ACTIVE",
        "formFactor": "SMALL",
        "ziaGateway": "",
        "zpaBroker": "",
        "buildVersion": "1.145.62_6.2.33187+17750d79",
        "upgradeStatus": 1,
        "upgradeStartTime": 0,
        "upgradeEndTime": 7200,
        "upgradeDayOfWeek": 1,
        "haStatus": "DISABLED",
        "useWanDns": false,
        "usedForZtp": false,
        "dnsCache": false,
        "failOpen": false,
        "ziaGateways": [],
        "zpaBrokers": []
      },
      {
        "id": 945931982,
        "name": "zs-cc-vpc-0fedcba9876543210-us-west-2-zscc-prod-cc-asg-1-3ofteftm-VM-7Ecaj",
        "status": [
          "REGISTERED",
          "PKG_REPO_REGISTERED",
          "AUTO_SCALE"
        ],
        "autoScale": true,
        "operationalStatus": "ACTIVE",
        "formFactor": "SMALL",
        "ziaGateway": "",
        "zpaBroker": "",
        "buildVersion": "1.145.62_6.2.33187+17750d79",
        "upgradeStatus": 1,
        "upgradeStartTime": 0,
        "upgradeEndTime": 7200,
        "upgradeDayOfWeek": 1,
        "haStatus": "DISABLED",
        "useWanDns": false,
        "usedForZtp": false,
        "dnsCache": false,
        "failOpen": false,
        "ziaGateways": [],
        "zpaBrokers": []
      },
      {
        "id": 615274987,
        "name": "zs-cc-vpc-0fedcba9876543210-us-west-2-zscc-prod-cc-asg-1-3ofteftm-VM-XfRWd",
        "status": [
          "REGISTERED",
          "PKG_REPO_REGISTERED",
          "AUTO_SCALE"
        ],
        "autoScale": true,
        "operationalStatus": "ACTIVE",
        "formFactor": "SMALL",
        "ziaGateway": "",
        "zpaBroker": "",
        "buildVersion": "1.145.62_6.2.33187+17750d79",
        "upgradeStatus": 1,
        "upgradeStartTime": 0,
        "upgradeEndTime": 7200,
        "upgradeDayOfWeek": 1,
        "haStatus": "DISABLED",
        "useWanDns": false,
        "usedForZtp": false,
        "dnsCache": false,
        "failOpen": false,
        "ziaGateways": [],
        "zpaBrokers": []
      },
      {
        "id": 712973410,
        "name": "zs-cc-vpc-0fedcba9876543210-us-west-2-zscc-prod-cc-asg-1-3ofteftm-VM-UfuyO",
        "status": [
          "REGISTERED",
          "PKG_REPO_REGISTERED",
          "AUTO_SCALE"
        ],
        "autoScale": true,
        "operationalStatus": "ACTIVE",
        "formFactor": "SMALL",
        "ziaGateway": "",
        "zpaBroker": "",
        "buildVersion": "1.145.62_6.2.33187+17750d79",
        "upgradeStatus": 1,
        "upgradeStartTime": 0,
        "upgradeEndTime": 7200,
        "upgradeDayOfWeek": 1,
        "haStatus": "DISABLED",
        "useWanDns": false,
        "usedForZtp": false,
        "dnsCache": false,
        "failOpen": false,
        "ziaGateways": [],
        "zpaBrokers": []
      }
    ]
  },
  {
    "id": 119057245,
    "name": "zs-cc-vpc-0ef2428df7e6c651c-us-east-1-zscc-prod-cc-asg-1-kovnzcx2",
    "deployType": "CLOUD",
    "fallBackToTls": false,
    "status": [
      "CLOUD",
      "AUTO_SCALE"
    ],
    "autoScale": true,
    "platform": "AWS",
    "awsRegion": "US_EAST_1",
    "location": {
      "id": 336702194,
      "name": "production-us_use1-us-east-1-vpc-0ef2428df7e6c651c"
    },
    "ecVMs": [
      {
        "id": 235967493,
        "name": "zs-cc-vpc-0ef2428df7e6c651c-us-east-1-zscc-prod-cc-asg-1-kovnzcx2-VM-Rfsqy",
        "status": [
          "REGISTERED",
          "PKG_REPO_REGISTERED",
          "AUTO_SCALE"
        ],
        "autoScale": true,
        "operationalStatus": "INACTIVE",
        "formFactor": "SMALL",
        "ziaGateway": "",
        "zpaBroker": "",
        "buildVersion": "0.209.6+5d1760079_6.2.29797+35e543fd",
        "upgradeStatus": 0,
        "upgradeStartTime": 0,
        "upgradeEndTime": 7200,
        "upgradeDayOfWeek": 1,
        "haStatus": "DISABLED",
        "useWanDns": false,
        "usedForZtp": false,
        "dnsCache": false,
        "failOpen": false,
        "ziaGateways": [],
        "zpaBrokers": []
      },
      {
        "id": 121786332,
        "name": "zs-cc-vpc-0ef2428df7e6c651c-us-east-1-zscc-prod-cc-asg-1-kovnzcx2-VM-yCvNC",
        "status": [
          "REGISTERED",
          "PKG_REPO_REGISTERED",
          "AUTO_SCALE"
        ],
        "autoScale": true,
        "operationalStatus": "INACTIVE",
        "formFactor": "SMALL",
        "ziaGateway": "",
        "zpaBroker": "",
        "buildVersion": "0.209.6+5d1760079_6.2.29797+35e543fd",
        "upgradeStatus": 0,
        "upgradeStartTime": 0,
        "upgradeEndTime": 7200,
        "upgradeDayOfWeek": 1,
        "haStatus": "DISABLED",
        "useWanDns": false,
        "usedForZtp": false,
        "dnsCache": false,
        "failOpen": false,
        "ziaGateways": [],
        "zpaBrokers": []
      },
      {
        "id": 928434260,
        "name": "zs-cc-vpc-0ef2428df7e6c651c-us-east-1-zscc-prod-cc-asg-1-kovnzcx2-VM-FdUBR",
        "status": [
          "REGISTERED",
          "PKG_REPO_REGISTERED",
          "AUTO_SCALE"
        ],
        "autoScale": true,
        "operationalStatus": "INACTIVE",
        "formFactor": "SMALL",
        "ziaGateway": "",
        "zpaBroker": "",
        "upgradeStatus": 1,
        "upgradeStartTime": 0,
        "upgradeEndTime": 7200,
        "upgradeDayOfWeek": 1,
        "haStatus": "DISABLED",
        "useWanDns": false,
        "usedForZtp": false,
        "dnsCache": false,
        "failOpen": false,
        "ziaGateways": [],
        "zpaBrokers": []
      },
      {
        "id": 779777681,
        "name": "zs-cc-vpc-0ef2428df7e6c651c-us-east-1-zscc-prod-cc-asg-1-kovnzcx2-VM-TZRhC",
        "status": [
          "REGISTERED",
          "PKG_REPO_REGISTERED",
          "AUTO_SCALE"
        ],
        "autoScale": true,
        "operationalStatus": "INACTIVE",
        "formFactor": "SMALL",
        "ziaGateway": "",
        "zpaBroker": "",
        "upgradeStatus": 1,
        "upgradeStartTime": 0,
        "upgradeEndTime": 7200,
        "upgradeDayOfWeek": 1,
        "haStatus": "DISABLED",
        "useWanDns": false,
        "usedForZtp": false,
        "dnsCache": false,
        "failOpen": false,
        "ziaGateways": [],
        "zpaBrokers": []
      },
      {
        "id": 679733816,
        "name": "zs-cc-vpc-0ef2428df7e6c651c-us-east-1-zscc-prod-cc-asg-1-kovnzcx2-VM-s9iHP",
        "status": [
          "REGISTERED",
          "PKG_REPO_REGISTERED",
          "AUTO_SCALE"
        ],
        "autoScale": true,
        "operationalStatus": "INACTIVE",
        "formFactor": "SMALL",
        "ziaGateway": "",
        "zpaBroker": "",
        "upgradeStatus": 1,
        "upgradeStartTime": 0,
        "upgradeEndTime": 7200,
        "upgradeDayOfWeek": 1,
        "haStatus": "DISABLED",
        "useWanDns": false,
        "usedForZtp": false,
        "dnsCache": false,
        "failOpen": false,
        "ziaGateways": [],
        "zpaBrokers": []
      },
      {
        "id": 781451477,
        "name": "zs-cc-vpc-0ef2428df7e6c651c-us-east-1-zscc-prod-cc-asg-1-kovnzcx2-VM-gp04m",
        "status": [
          "REGISTERED",
          "PKG_REPO_REGISTERED",
          "AUTO_SCALE"
        ],
        "autoScale": true,
        "operationalStatus": "INACTIVE",
        "formFactor": "SMALL",
        "ziaGateway": "",
        "zpaBroker": "",
        "upgradeStatus": 1,
        "upgradeStartTime": 0,
        "upgradeEndTime": 7200,
        "upgradeDayOfWeek": 1,
        "haStatus": "DISABLED",
        "useWanDns": false,
        "usedForZtp": false,
        "dnsCache": false,
        "failOpen": false,
        "ziaGateways": [],
        "zpaBrokers": []
      },
      {
        "id": 736670007,
        "name": "zs-cc-vpc-0ef2428df7e6c651c-us-east-1-zscc-prod-cc-asg-1-kovnzcx2-VM-53Bfj",
        "status": [
          "REGISTERED",
          "PKG_REPO_REGISTERED",
          "AUTO_SCALE"
        ],
        "autoScale": true,
        "operationalStatus": "ACTIVE",
        "formFactor": "SMALL",
        "ziaGateway": "",
        "zpaBroker": "",
        "buildVersion": "1.145.62_6.2.33187+17750d79",
        "upgradeStatus": 1,
        "upgradeStartTime": 0,
        "upgradeEndTime": 7200,
        "upgradeDayOfWeek": 1,
        "haStatus": "DISABLED",
        "useWanDns": false,
        "usedForZtp": false,
        "dnsCache": false,
        "failOpen": false,
        "ziaGateways": [],
        "zpaBrokers": []
      },
      {
        "id": 826138359,
        "name": "zs-cc-vpc-0ef2428df7e6c651c-us-east-1-zscc-prod-cc-asg-1-kovnzcx2-VM-Xfxg6",
        "status": [
          "REGISTERED",
          "PKG_REPO_REGISTERED",
          "AUTO_SCALE"
        ],
        "autoScale": true,
        "operationalStatus": "ACTIVE",
        "formFactor": "SMALL",
        "ziaGateway": "",
        "zpaBroker": "",
        "buildVersion": "1.145.62_6.2.33187+17750d79",
        "upgradeStatus": 1,
        "upgradeStartTime": 0,
        "upgradeEndTime": 7200,
        "upgradeDayOfWeek": 1,
        "haStatus": "DISABLED",
        "useWanDns": false,
        "usedForZtp": false,
        "dnsCache": false,
        "failOpen": false,
        "ziaGateways": [],
        "zpaBrokers": []
      },
      {
        "id": 559780078,
        "name": "zs-cc-vpc-0ef2428df7e6c651c-us-east-1-zscc-prod-cc-asg-1-kovnzcx2-VM-Yqa5l",
        "status": [
          "REGISTERED",
          "PKG_REPO_REGISTERED",
          "AUTO_SCALE"
        ],
        "autoScale": true,
        "operationalStatus": "INACTIVE",
        "formFactor": "SMALL",
        "ziaGateway": "",
        "zpaBroker": "",
        "upgradeStatus": 1,
        "upgradeStartTime": 0,
        "upgradeEndTime": 7200,
        "upgradeDayOfWeek": 1,
        "haStatus": "DISABLED",
        "useWanDns": false,
        "usedForZtp": false,
        "dnsCache": false,
        "failOpen": false,
        "ziaGateways": [],
        "zpaBrokers": []
      },
      {
        "id": 199768358,
        "name": "zs-cc-vpc-0ef2428df7e6c651c-us-east-1-zscc-prod-cc-asg-1-kovnzcx2-VM-AroT3",
        "status": [
          "REGISTERED",
          "PKG_REPO_REGISTERED",
          "AUTO_SCALE"
        ],
        "autoScale": true,
        "operationalStatus": "INACTIVE",
        "formFactor": "SMALL",
        "ziaGateway": "",
        "zpaBroker": "",
        "upgradeStatus": 1,
        "upgradeStartTime": 0,
        "upgradeEndTime": 7200,
        "upgradeDayOfWeek": 1,
        "haStatus": "DISABLED",
        "useWanDns": false,
        "usedForZtp": false,
        "dnsCache": false,
        "failOpen": false,
        "ziaGateways": [],
        "zpaBrokers": []
      }
    ]
  }
]